lightmodelfactory/__init__.py
lightmodelfactory/data/__init__.py
lightmodelfactory/data/data_attr.py
lightmodelfactory/data/loader.py
lightmodelfactory/main/callback.py
lightmodelfactory/main/main.py
lightmodelfactory/plugins/__init__.py
lightmodelfactory/plugins/ds_zero2_no_offload.json
lightmodelfactory/plugins/flag_embedding/__init__.py
lightmodelfactory/plugins/flag_embedding/embedding_type.json
lightmodelfactory/plugins/flag_embedding/plugin.py
lightmodelfactory/plugins/llama_factory/__init__.py
lightmodelfactory/plugins/llama_factory/fsdp_config.yaml
lightmodelfactory/plugins/llama_factory/model_lora_target.json
lightmodelfactory/plugins/llama_factory/model_template.json
lightmodelfactory/plugins/llama_factory/plugin.py
lightmodelfactory/plugins/llama_factory/read_progress.py
lightmodelfactory/plugins/plugin.py
lightmodelfactory/plugins/plugin_build.py
lightmodelfactory/plugins/spark/__init__.py
lightmodelfactory/plugins/spark/plugin.py
lightmodelfactory/plugins/swift/__init__.py
lightmodelfactory/plugins/swift/plugin.py
lightmodelfactory/plugins/swift/read_progress.py
lightmodelfactory/plugins/xtuner/__init__.py
lightmodelfactory/util/__init__.py
lightmodelfactory/util/calc_token.py
lightmodelfactory/util/check_machine.py
lightmodelfactory/util/logger.py
lightmodelfactory/util/other.py
lightmodelfactory/util/param.py
lightmodelfactory/util/parse_error.py
lightmodelfactory-0.0.2.dist-info/METADATA
lightmodelfactory-0.0.2.dist-info/WHEEL
lightmodelfactory-0.0.2.dist-info/RECORD
