Metadata-Version: 2.1
Name: lightmodelfactory
Version: 0.0.2
Summary: a lightmodelfactory library
License: Apache License 2
Author: mjchen
Author-email: mjchen@iflytek.com
Requires-Python: >3.9
Classifier: License :: Other/Proprietary License
Classifier: Programming Language :: Python :: 3
Classifier: Programming Language :: Python :: 3.10
Classifier: Programming Language :: Python :: 3.11
